{
  "fixture_id": "B-locked-non-retroactive",
  "description": "Locked visit keeps V1 classification after V2 publishes wider window that would reclassify",
  "important_codes": ["V2"],
  "versions": [
    {
      "id": "V1",
      "effective_at": "2026-01-01",
      "visits": {
        "V2": { "target_day": 28, "before": 1, "after": 1 }
      }
    },
    {
      "id": "V2",
      "effective_at": "2026-02-01",
      "visits": {
        "V2": { "target_day": 28, "before": 14, "after": 14 }
      }
    }
  ],
  "subject": { "id": "S1", "enrollment": "2026-01-01" },
  "cases": [
    {
      "visit": {
        "code": "V2",
        "actual": "2026-01-30",
        "locked": true,
        "scored_version_id": "V1",
        "classification": "out_of_window"
      },
      "expect": {
        "version_id": "V1",
        "classification": "out_of_window",
        "important": true,
        "note": "would be on_time under V2; lock must win"
      }
    }
  ]
}
